[
    {
        "key": "key_922454",
        "value": 0.29973154841053107
    },
    {
        "key": "key_746664",
        "value": 0.010791225342454247
    },
    {
        "key": "key_882786",
        "value": 0.22769040178078281
    },
    {
        "key": "key_932994",
        "value": 0.09264301610064984
    },
    {
        "key": "key_379510",
        "value": 0.3317957004494727
    },
    {
        "key": "key_725057",
        "value": 0.2520156832274888
    },
    {
        "key": "key_275182",
        "value": 0.7274275644436049
    },
    {
        "key": "key_731459",
        "value": 0.9692035901360561
    },
    {
        "key": "key_327161",
        "value": 0.7699144445357144
    },
    {
        "key": "key_151795",
        "value": 0.7891978411027627
    },
    {
        "key": "key_383170",
        "value": 0.17142027039103536
    },
    {
        "key": "key_762339",
        "value": 0.44145220510113237
    },
    {
        "key": "key_895882",
        "value": 0.5964313615434221
    },
    {
        "key": "key_977202",
        "value": 0.6228256719578421
    },
    {
        "key": "key_26449",
        "value": 0.14758765262570206
    },
    {
        "key": "key_725396",
        "value": 0.5071938603743734
    },
    {
        "key": "key_915953",
        "value": 0.6649457878918215
    },
    {
        "key": "key_193611",
        "value": 0.16873359722190495
    },
    {
        "key": "key_794994",
        "value": 0.5332979895560782
    },
    {
        "key": "key_623125",
        "value": 0.3225376356500692
    },
    {
        "key": "key_436666",
        "value": 0.7657671198900444
    },
    {
        "key": "key_151798",
        "value": 0.1345949770291649
    },
    {
        "key": "key_162468",
        "value": 0.6755077195082029
    },
    {
        "key": "key_185638",
        "value": 0.9894835950314985
    },
    {
        "key": "key_86932",
        "value": 0.8232585516760931
    },
    {
        "key": "key_655275",
        "value": 0.34757263409345074
    },
    {
        "key": "key_488108",
        "value": 0.21072290655998804
    },
    {
        "key": "key_181349",
        "value": 0.1415160266192168
    },
    {
        "key": "key_922949",
        "value": 0.3067170999982999
    },
    {
        "key": "key_608278",
        "value": 0.33036695551223016
    },
    {
        "key": "key_192096",
        "value": 0.005782278821905074
    },
    {
        "key": "key_425163",
        "value": 0.007232228888410797
    },
    {
        "key": "key_422121",
        "value": 0.16024342952851667
    },
    {
        "key": "key_844616",
        "value": 0.08187083257792582
    },
    {
        "key": "key_294931",
        "value": 0.14550185001126414
    },
    {
        "key": "key_130574",
        "value": 0.07902627586211597
    },
    {
        "key": "key_709895",
        "value": 0.008946637845508532
    },
    {
        "key": "key_985635",
        "value": 0.2032726712158307
    },
    {
        "key": "key_87670",
        "value": 0.14687114583398297
    },
    {
        "key": "key_712892",
        "value": 0.49954536349946754
    },
    {
        "key": "key_945604",
        "value": 0.36323221873570477
    },
    {
        "key": "key_531916",
        "value": 0.7739247802383518
    },
    {
        "key": "key_110239",
        "value": 0.14524176246139098
    },
    {
        "key": "key_108949",
        "value": 0.332347688645965
    },
    {
        "key": "key_604942",
        "value": 0.10945447250461526
    },
    {
        "key": "key_708234",
        "value": 0.9599567978818645
    },
    {
        "key": "key_258097",
        "value": 0.42704160973162986
    },
    {
        "key": "key_692712",
        "value": 0.006402980966519256
    },
    {
        "key": "key_730319",
        "value": 0.9739324870323888
    },
    {
        "key": "key_609429",
        "value": 0.6058772041616983
    },
    {
        "key": "key_558610",
        "value": 0.5864988302063645
    },
    {
        "key": "key_659045",
        "value": 0.25367088809150073
    },
    {
        "key": "key_205463",
        "value": 0.8120631878952181
    },
    {
        "key": "key_99900",
        "value": 0.969729857699916
    },
    {
        "key": "key_535358",
        "value": 0.8974462513264785
    },
    {
        "key": "key_731627",
        "value": 0.017365579063969405
    },
    {
        "key": "key_385583",
        "value": 0.8144045289978061
    },
    {
        "key": "key_7318",
        "value": 0.26116983467304355
    },
    {
        "key": "key_114928",
        "value": 0.5968284093170055
    },
    {
        "key": "key_431685",
        "value": 0.796937069915052
    },
    {
        "key": "key_676291",
        "value": 0.26761516248716866
    },
    {
        "key": "key_48007",
        "value": 0.8274691755321879
    },
    {
        "key": "key_707978",
        "value": 0.3983005215162786
    },
    {
        "key": "key_831728",
        "value": 0.8909675179173321
    },
    {
        "key": "key_297457",
        "value": 0.345893618858082
    },
    {
        "key": "key_698167",
        "value": 0.854804068299723
    },
    {
        "key": "key_674413",
        "value": 0.41509398699863487
    },
    {
        "key": "key_554162",
        "value": 0.2798912608665979
    },
    {
        "key": "key_502852",
        "value": 0.416806282782032
    },
    {
        "key": "key_689310",
        "value": 0.5854914771368814
    },
    {
        "key": "key_486760",
        "value": 0.4019134340036139
    },
    {
        "key": "key_449843",
        "value": 0.9097837475270049
    },
    {
        "key": "key_544592",
        "value": 0.4946643053152209
    },
    {
        "key": "key_136677",
        "value": 0.10418786092974419
    },
    {
        "key": "key_719654",
        "value": 0.1845762783435747
    },
    {
        "key": "key_669736",
        "value": 0.357249952726188
    },
    {
        "key": "key_302608",
        "value": 0.3681432889368891
    },
    {
        "key": "key_993848",
        "value": 0.35093947399279646
    },
    {
        "key": "key_700953",
        "value": 0.9809048681525505
    },
    {
        "key": "key_136361",
        "value": 0.9366577291239687
    },
    {
        "key": "key_168160",
        "value": 0.6760614131897553
    },
    {
        "key": "key_377782",
        "value": 0.9593419027729496
    },
    {
        "key": "key_1367",
        "value": 0.24856551876821087
    },
    {
        "key": "key_319529",
        "value": 0.7637145499635973
    },
    {
        "key": "key_86998",
        "value": 0.5396877647438669
    },
    {
        "key": "key_762456",
        "value": 0.20457045393184015
    },
    {
        "key": "key_180038",
        "value": 0.3993692312957966
    },
    {
        "key": "key_494560",
        "value": 0.3584931154247222
    },
    {
        "key": "key_109839",
        "value": 0.7527973173760217
    },
    {
        "key": "key_838538",
        "value": 0.9374914302509552
    },
    {
        "key": "key_375490",
        "value": 0.9958749546567003
    },
    {
        "key": "key_386411",
        "value": 0.10851258610954195
    },
    {
        "key": "key_461281",
        "value": 0.2961216246056386
    },
    {
        "key": "key_267715",
        "value": 0.32400254501943315
    },
    {
        "key": "key_691102",
        "value": 0.14411294070598046
    },
    {
        "key": "key_515357",
        "value": 0.0025657979711352086
    },
    {
        "key": "key_911257",
        "value": 0.46565584007804295
    },
    {
        "key": "key_97958",
        "value": 0.4970849431471501
    },
    {
        "key": "key_517920",
        "value": 0.010743979290537276
    },
    {
        "key": "key_962790",
        "value": 0.4558013434733862
    },
    {
        "key": "key_308082",
        "value": 0.27740569894194844
    },
    {
        "key": "key_852332",
        "value": 0.7245079301917637
    },
    {
        "key": "key_878456",
        "value": 0.7735589355683978
    },
    {
        "key": "key_136068",
        "value": 0.4364671226935962
    },
    {
        "key": "key_865701",
        "value": 0.873744714678922
    },
    {
        "key": "key_386797",
        "value": 0.09471235236022824
    },
    {
        "key": "key_960026",
        "value": 0.27904728159919256
    },
    {
        "key": "key_689278",
        "value": 0.8806556596686503
    },
    {
        "key": "key_718387",
        "value": 0.4890196268534349
    },
    {
        "key": "key_215522",
        "value": 0.012798956791768346
    },
    {
        "key": "key_967754",
        "value": 0.7738668051219051
    },
    {
        "key": "key_516252",
        "value": 0.21453442182396476
    },
    {
        "key": "key_332379",
        "value": 0.1526882366279061
    },
    {
        "key": "key_700389",
        "value": 0.8704472079916431
    },
    {
        "key": "key_861537",
        "value": 0.1539481317886373
    },
    {
        "key": "key_667901",
        "value": 0.33538105994948086
    },
    {
        "key": "key_607291",
        "value": 0.006422854247949417
    },
    {
        "key": "key_719658",
        "value": 0.5578242541316705
    },
    {
        "key": "key_407218",
        "value": 0.17384021455296061
    },
    {
        "key": "key_872140",
        "value": 0.16240289274354813
    },
    {
        "key": "key_318562",
        "value": 0.12400819049995349
    },
    {
        "key": "key_745612",
        "value": 0.5232005569896852
    },
    {
        "key": "key_519677",
        "value": 0.18189844695070334
    },
    {
        "key": "key_979643",
        "value": 0.38313620258190784
    },
    {
        "key": "key_769269",
        "value": 0.6827457711211332
    },
    {
        "key": "key_134738",
        "value": 0.3873657200507984
    },
    {
        "key": "key_730486",
        "value": 0.7348702441685758
    },
    {
        "key": "key_149586",
        "value": 0.046352127279389865
    },
    {
        "key": "key_650446",
        "value": 0.07509223748786842
    },
    {
        "key": "key_74850",
        "value": 0.48694142952506747
    },
    {
        "key": "key_133896",
        "value": 0.9336270391614729
    },
    {
        "key": "key_486849",
        "value": 0.6979171013738477
    },
    {
        "key": "key_302705",
        "value": 0.5985193722704277
    },
    {
        "key": "key_81913",
        "value": 0.7189478589130093
    },
    {
        "key": "key_53183",
        "value": 0.9711332921120233
    },
    {
        "key": "key_286596",
        "value": 0.7883495790348709
    },
    {
        "key": "key_803426",
        "value": 0.7567193305777745
    },
    {
        "key": "key_462104",
        "value": 0.6653785587615572
    },
    {
        "key": "key_324895",
        "value": 0.15322393937504553
    },
    {
        "key": "key_324849",
        "value": 0.8259411585169809
    },
    {
        "key": "key_896458",
        "value": 0.1830751257452784
    },
    {
        "key": "key_87916",
        "value": 0.6408406662889523
    },
    {
        "key": "key_399095",
        "value": 0.5555081411796594
    },
    {
        "key": "key_429340",
        "value": 0.9727381510510069
    },
    {
        "key": "key_666216",
        "value": 0.9814581643071826
    },
    {
        "key": "key_899541",
        "value": 0.07660394499473522
    },
    {
        "key": "key_780731",
        "value": 0.7550006123751812
    },
    {
        "key": "key_430707",
        "value": 0.8333750037627431
    },
    {
        "key": "key_739932",
        "value": 0.18120075719137851
    },
    {
        "key": "key_412515",
        "value": 0.9042662213591143
    },
    {
        "key": "key_665649",
        "value": 0.5632840347110576
    },
    {
        "key": "key_137592",
        "value": 0.05753004735725986
    },
    {
        "key": "key_64537",
        "value": 0.8032306060434337
    },
    {
        "key": "key_75270",
        "value": 0.28560636156518715
    },
    {
        "key": "key_783264",
        "value": 0.5446932494595765
    },
    {
        "key": "key_602463",
        "value": 0.0831723085569479
    },
    {
        "key": "key_505481",
        "value": 0.4900995683895226
    },
    {
        "key": "key_285014",
        "value": 0.9633680208605706
    },
    {
        "key": "key_43532",
        "value": 0.6198001432843266
    },
    {
        "key": "key_562674",
        "value": 0.5493832155490646
    }
]